greg_test/__init__.py
greg_test/__main__.py
greg_test/cli.py
greg_test/core.py
greg_test/version.py
greg_test-0.1.dist-info/entry_points.txt
greg_test-0.1.dist-info/LICENSE
greg_test-0.1.dist-info/WHEEL
greg_test-0.1.dist-info/METADATA
greg_test-0.1.dist-info/RECORD
